ai4_api_keys/__init__.py
ai4_api_keys/cli/__init__.py
ai4_api_keys/cli/fernet.py
ai4_api_keys/cli/keys.py
ai4_api_keys/exceptions.py
ai4_api_keys/fernet.py
ai4_api_keys/keys.py
ai4_api_keys/tests/__init__.py
ai4_api_keys/tests/test_fernet.py
ai4_api_keys/tests/test_keys.py
ai4_api_keys-0.1.0.dist-info/METADATA
ai4_api_keys-0.1.0.dist-info/WHEEL
ai4_api_keys-0.1.0.dist-info/entry_points.txt
ai4_api_keys-0.1.0.dist-info/RECORD
