Metadata-Version: 2.1
Name: ai4-api-keys
Version: 0.1.0
Summary: AI4 API Key generator
Home-page: https://github.com/ai4os/ai4-api-keys
License: MIT
Author: Alvaro Lopez Garcia
Author-email: aloga@ifca.unican.es
Requires-Python: >=3.10,<4.0
Classifier: License :: OSI Approved :: MIT License
Classifier: Programming Language :: Python :: 3
Classifier: Programming Language :: Python :: 3.10
Classifier: Programming Language :: Python :: 3.11
Classifier: Programming Language :: Python :: 3.12
Classifier: Programming Language :: Python :: 3.13
Requires-Dist: cryptography (>=43.0.1,<44.0.0)
Requires-Dist: typer (>=0.12.5,<0.13.0)
Project-URL: Bug Tracker, https://github.com/ai4os/ai4-api-keys/issues
Project-URL: Repository, https://github.com/ai4os/ai4-api-keys
